CHANGES.rst
MANIFEST.in
README.rst
setup.py
docs/LICENSE-GPL.rst
src/collective/__init__.py
src/collective.portlet.collectionfilter.egg-info/PKG-INFO
src/collective.portlet.collectionfilter.egg-info/SOURCES.txt
src/collective.portlet.collectionfilter.egg-info/dependency_links.txt
src/collective.portlet.collectionfilter.egg-info/entry_points.txt
src/collective.portlet.collectionfilter.egg-info/namespace_packages.txt
src/collective.portlet.collectionfilter.egg-info/not-zip-safe
src/collective.portlet.collectionfilter.egg-info/requires.txt
src/collective.portlet.collectionfilter.egg-info/top_level.txt
src/collective/portlet/__init__.py
src/collective/portlet/collectionfilter/__init__.py
src/collective/portlet/collectionfilter/collectionfilter.pt
src/collective/portlet/collectionfilter/collectionfilter.py
src/collective/portlet/collectionfilter/collectionsearch.pt
src/collective/portlet/collectionfilter/collectionsearch.py
src/collective/portlet/collectionfilter/configure.zcml
src/collective/portlet/collectionfilter/content_filter.py
src/collective/portlet/collectionfilter/indexer.py
src/collective/portlet/collectionfilter/utils.py
src/collective/portlet/collectionfilter/vocabularies.py
src/collective/portlet/collectionfilter/locales/collective.portlet.collectionfilter.pot
src/collective/portlet/collectionfilter/locales/de/LC_MESSAGES/collective.portlet.collectionfilter.po
src/collective/portlet/collectionfilter/profiles/default/metadata.xml
src/collective/portlet/collectionfilter/profiles/default/portlets.xml
src/collective/portlet/collectionfilter/tests/__init__.py
src/collective/portlet/collectionfilter/tests/base.py
src/collective/portlet/collectionfilter/tests/test_portlet.py