Metadata-Version: 1.1
Name: collective.portlet.collectionfilter
Version: 1.4.1
Summary: Portlets for filtering collection results.
Home-page: http://github.com/collective/collective.portlet.collectionfilter
Author: Johannes Raggam
Author-email: johannes@raggam.co.at
License: GPL
Keywords: plone portlet collection filter faceted tagcloud tags
Platform: UNKNOWN
Classifier: Framework :: Plone
Classifier: Programming Language :: Python
Classifier: Topic :: Software Development :: Libraries :: Python Modules
